pydbox/__init__.py
pydbox/tesi/__init__.py
pydbox/tesi/tesi.py
pydbox-0.1.0.dist-info/licenses/LICENSE
pydbox-0.1.0.dist-info/METADATA
pydbox-0.1.0.dist-info/WHEEL
pydbox-0.1.0.dist-info/top_level.txt
pydbox-0.1.0.dist-info/RECORD
